video_to_slides/__init__.py
video_to_slides-0.1.0.dist-info/entry_points.txt
video_to_slides-0.1.0.dist-info/LICENSE
video_to_slides-0.1.0.dist-info/WHEEL
video_to_slides-0.1.0.dist-info/METADATA
video_to_slides-0.1.0.dist-info/RECORD
