Metadata-Version: 2.1
Name: video-to-slides
Version: 0.1.0
Summary: Convert video to pdf slides.
Home-page: https://github.com/0scarB/video-to-slides
License: MIT
Keywords: video,pdf,slides,convert,presentation
Author: 0scarB
Author-email: oscarb@protonmail.com
Requires-Python: >=3.7,<4.0
Classifier: Environment :: Console
Classifier: License :: OSI Approved :: MIT License
Classifier: Programming Language :: Python :: 3
Classifier: Programming Language :: Python :: 3.7
Classifier: Programming Language :: Python :: 3.8
Classifier: Programming Language :: Python :: 3.9
Classifier: Topic :: Multimedia :: Video
Classifier: Topic :: Scientific/Engineering :: Image Processing
Requires-Dist: PyMuPDF (>=1.18.17,<2.0.0)
Requires-Dist: click (>=8.0.1,<9.0.0)
Requires-Dist: opencv-python (>=4.5.3,<5.0.0)
Requires-Dist: pytesseract (>=0.3.8,<0.4.0)
Requires-Dist: rapidfuzz (>=1.5.0,<2.0.0)
Requires-Dist: tesseract (>=0.1.3,<0.2.0)
Requires-Dist: tqdm (>=4.62.2,<5.0.0)
Project-URL: Documentation, https://github.com/0scarB/video-to-slides
Project-URL: Repository, https://github.com/0scarB/video-to-slides
